cf_units-3.3.1.dist-info/RECORD
cf_units-3.3.1.dist-info/WHEEL
cf_units-3.3.1.dist-info/top_level.txt
cf_units-3.3.1.dist-info/METADATA
cf_units-3.3.1.dist-info/licenses/LICENSE
cf_units/_udunits2.pyx
cf_units/_udunits2.c
cf_units/config.py
cf_units/tex.py
cf_units/_version.py
cf_units/util.py
cf_units/__init__.py
cf_units/_udunits2.abi3.so
cf_units/_udunits2.pxd
cf_units/tests/test_coding_standards.py
cf_units/tests/__init__.py
cf_units/tests/test_tex.py
cf_units/tests/test_unit.py
cf_units/tests/unit/__init__.py
cf_units/tests/unit/test__udunits2.py
cf_units/tests/unit/unit/test_Unit.py
cf_units/tests/unit/unit/test_as_unit.py
cf_units/tests/integration/test_num2date.py
cf_units/tests/integration/__init__.py
cf_units/tests/integration/test__Unit_num2date.py
cf_units/tests/integration/test_num2pydate.py
cf_units/tests/integration/test_date2num.py
cf_units/tests/integration/test__Unit_date2num.py
cf_units/tests/integration/parse/test_parse.py
cf_units/tests/integration/parse/test_graph.py
cf_units/etc/site.cfg.template
cf_units/etc/share/udunits2-prefixes.xml
cf_units/etc/share/udunits2.xml
cf_units/etc/share/udunits2-common.xml
cf_units/etc/share/udunits2-derived.xml
cf_units/etc/share/udunits2-accepted.xml
cf_units/etc/share/udunits2-base.xml
cf_units/.dylibs/libudunits2.0.dylib
cf_units/_udunits2_parser/graph.py
cf_units/_udunits2_parser/__init__.py
cf_units/_udunits2_parser/README.md
cf_units/_udunits2_parser/udunits2Parser.g4
cf_units/_udunits2_parser/.gitignore
cf_units/_udunits2_parser/compile.py
cf_units/_udunits2_parser/udunits2Lexer.g4.jinja
cf_units/_udunits2_parser/parser/udunits2Parser.py
cf_units/_udunits2_parser/parser/__init__.py
cf_units/_udunits2_parser/parser/udunits2ParserVisitor.py
cf_units/_udunits2_parser/parser/udunits2Lexer.py
cf_units/_udunits2_parser/_antlr4_runtime/CommonTokenFactory.py
cf_units/_udunits2_parser/_antlr4_runtime/Token.py
cf_units/_udunits2_parser/_antlr4_runtime/InputStream.py
cf_units/_udunits2_parser/_antlr4_runtime/FileStream.py
cf_units/_udunits2_parser/_antlr4_runtime/ListTokenSource.py
cf_units/_udunits2_parser/_antlr4_runtime/Recognizer.py
