Metadata-Version: 2.4
Name: cf-units
Version: 3.3.1
Summary: Units of measure as required by the Climate and Forecast (CF) metadata conventions
Author-email: cf-units Contributors <scitools.pub@gmail.com>
License-Expression: BSD-3-Clause
Project-URL: Code, https://github.com/SciTools/cf-units
Project-URL: Discussions, https://github.com/SciTools/cf-units/discussions
Project-URL: Documentation, https://cf-units.readthedocs.io
Project-URL: Issues, https://github.com/SciTools/cf-units/issues
Keywords: units,cf,cf-metadata,netcdf,science,earth-science,oceanography,meteorology,climate,python
Classifier: Development Status :: 5 - Production/Stable
Classifier: Intended Audience :: Science/Research
Classifier: Operating System :: OS Independent
Classifier: Programming Language :: Python
Classifier: Programming Language :: Python :: 3 :: Only
Classifier: Programming Language :: Python :: 3.11
Classifier: Programming Language :: Python :: 3.12
Classifier: Programming Language :: Python :: 3.13
Classifier: Programming Language :: Python :: 3.14
Classifier: Programming Language :: Python :: Implementation :: CPython
Classifier: Topic :: Scientific/Engineering
Classifier: Topic :: Scientific/Engineering :: Atmospheric Science
Classifier: Topic :: Scientific/Engineering :: Oceanography
Requires-Python: >=3.11
License-File: LICENSE
Requires-Dist: cftime>=1.2
Requires-Dist: jinja2
Requires-Dist: numpy
Provides-Extra: all
Requires-Dist: cf-units[docs,test]; extra == "all"
Provides-Extra: docs
Requires-Dist: sphinx; extra == "docs"
Provides-Extra: test
Requires-Dist: codecov; extra == "test"
Requires-Dist: cython; extra == "test"
Requires-Dist: jinja2; extra == "test"
Requires-Dist: pip; extra == "test"
Requires-Dist: pytest; extra == "test"
Requires-Dist: pytest-cov; extra == "test"
Requires-Dist: tomli; extra == "test"
Dynamic: license-file
